sqliteSession/__init__.py
sqliteSession/sql.py
Sqlite_Session-0.1.0.dist-info/LICENSE
Sqlite_Session-0.1.0.dist-info/METADATA
Sqlite_Session-0.1.0.dist-info/WHEEL
Sqlite_Session-0.1.0.dist-info/top_level.txt
Sqlite_Session-0.1.0.dist-info/RECORD
