Metadata-Version: 2.1
Name: Sqlite-Session
Version: 0.1.0
Summary: Use SQLite to store session data on the server.
Home-page: https://github.com/lc6464/Sqlite-Session
License: MIT License
Platform: UNKNOWN
